eval/__init__.py
eval/__main__.py
eval/evaluator.py
eval/interpreter.py
eval/lexer.py
eval/parse.py
eval/tokens.py
eval/values.py
expression_parse_eval-0.13.0.dist-info/LICENSE
expression_parse_eval-0.13.0.dist-info/METADATA
expression_parse_eval-0.13.0.dist-info/WHEEL
expression_parse_eval-0.13.0.dist-info/entry_points.txt
expression_parse_eval-0.13.0.dist-info/top_level.txt
expression_parse_eval-0.13.0.dist-info/RECORD
