Metadata-Version: 2.1
Name: expression-parse-eval
Version: 0.13.0
Summary: Mathematical expression calculator in Python
Home-page: https://github.com/poyea/eval
Author: John Law
Author-email: johnlaw.po@gmail.com
License: MIT
Platform: UNKNOWN
Classifier: License :: OSI Approved :: MIT License
Classifier: Programming Language :: Python :: 3.9
License-File: LICENSE
